ailib/__about__.py
ailib/__init__.py
ailib_full-0.1.0.dist-info/METADATA
ailib_full-0.1.0.dist-info/WHEEL
ailib_full-0.1.0.dist-info/RECORD
