Metadata-Version: 2.1
Name: ailib-full
Version: 0.1.0
Summary: AILib is a library for multiple languages to use various AI models that I find interesting
Project-URL: Documentation, https://github.com/CyberDie22/ailib#readme
Project-URL: Issues, https://github.com/CyberDie22/ailib/issues
Project-URL: Source, https://github.com/CyberDie22/ailib
Author-email: Ben Buzard <ben@benbuzard.com>
License-Expression: MIT
Classifier: Development Status :: 4 - Beta
Classifier: Programming Language :: Python
Classifier: Programming Language :: Python :: 3.7
Classifier: Programming Language :: Python :: 3.8
Classifier: Programming Language :: Python :: 3.9
Classifier: Programming Language :: Python :: 3.10
Classifier: Programming Language :: Python :: 3.11
Classifier: Programming Language :: Python :: Implementation :: CPython
Classifier: Programming Language :: Python :: Implementation :: PyPy
Requires-Python: >=3.7
